{
  "indexes": [
    {
      "collectionGroup": "workoutSessions",
      "queryScope": "COLLECTION",
      "fields": [
        {
          "fieldPath": "guestUid",
          "order": "ASCENDING"
        },
        {
          "fieldPath": "status",
          "order": "ASCENDING"
        },
        {
          "fieldPath": "scheduledAt",
          "order": "ASCENDING"
        }
      ]
    },
    {
      "collectionGroup": "workoutSessions",
      "queryScope": "COLLECTION",
      "fields": [
        {
          "fieldPath": "hostUid",
          "order": "ASCENDING"
        },
        {
          "fieldPath": "status",
          "order": "ASCENDING"
        },
        {
          "fieldPath": "scheduledAt",
          "order": "ASCENDING"
        }
      ]
    },
    {
      "collectionGroup": "scheduledWorkouts",
      "queryScope": "COLLECTION",
      "fields": [
        {
          "fieldPath": "status",
          "order": "ASCENDING"
        },
        {
          "fieldPath": "scheduledAt",
          "order": "ASCENDING"
        }
      ]
    },
    {
      "collectionGroup": "scheduledWorkouts",
      "queryScope": "COLLECTION",
      "fields": [
        {
          "fieldPath": "userId",
          "order": "ASCENDING"
        },
        {
          "fieldPath": "status",
          "order": "ASCENDING"
        },
        {
          "fieldPath": "scheduledAt",
          "order": "ASCENDING"
        }
      ]
    },
    {
      "collectionGroup": "scheduledWorkouts",
      "queryScope": "COLLECTION",
      "fields": [
        {
          "fieldPath": "userId",
          "order": "ASCENDING"
        },
        {
          "fieldPath": "status",
          "order": "ASCENDING"
        },
        {
          "fieldPath": "reminderScheduledFor",
          "order": "ASCENDING"
        }
      ]
    },
    {
      "collectionGroup": "scheduledWorkouts",
      "queryScope": "COLLECTION",
      "fields": [
        {
          "fieldPath": "status",
          "order": "ASCENDING"
        },
        {
          "fieldPath": "userId",
          "order": "ASCENDING"
        },
        {
          "fieldPath": "scheduledFor",
          "order": "ASCENDING"
        }
      ]
    },
    {
      "collectionGroup": "scheduledWorkouts",
      "queryScope": "COLLECTION",
      "fields": [
        {
          "fieldPath": "status",
          "order": "ASCENDING"
        },
        {
          "fieldPath": "userId",
          "order": "ASCENDING"
        },
        {
          "fieldPath": "workoutId",
          "order": "ASCENDING"
        },
        {
          "fieldPath": "scheduledFor",
          "order": "ASCENDING"
        }
      ]
    },
    {
      "collectionGroup": "scheduledWorkouts",
      "queryScope": "COLLECTION",
      "fields": [
        { "fieldPath": "videoId", "order": "ASCENDING" },
        { "fieldPath": "status", "order": "ASCENDING" }
      ]
    },
    {
      "collectionGroup": "scheduledWorkouts",
      "queryScope": "COLLECTION",
      "fields": [
        { "fieldPath": "workoutId", "order": "ASCENDING" },
        { "fieldPath": "status", "order": "ASCENDING" }
      ]
    }
  ],
  "fieldOverrides": []
}
